emulo/__init__.py
emulo/api/__init__.py
emulo/api/base_api.py
emulo/api/client.py
emulo/api/models.py
emulo/api/rate_limiter.py
emulo/api/crypto_prices/__init__.py
emulo/api/crypto_prices/binance.py
emulo/api/crypto_prices/chainlink.py
emulo/api/crypto_prices/namespace.py
emulo/api/kalshi/__init__.py
emulo/api/kalshi/markets.py
emulo/api/kalshi/namespace.py
emulo/api/kalshi/orderbooks.py
emulo/api/kalshi/trades.py
emulo/api/matching_markets/__init__.py
emulo/api/matching_markets/namespace.py
emulo/api/polymarket/__init__.py
emulo/api/polymarket/activity.py
emulo/api/polymarket/markets.py
emulo/api/polymarket/namespace.py
emulo/api/polymarket/orders.py
emulo/api/polymarket/wallet.py
emulo/api/polymarket/websocket.py
emulo/models/__init__.py
emulo/models/result.py
emulo/native/__init__.py
emulo/native/kalshi.py
emulo/native/polymarket.py
emulo/simulation/__init__.py
emulo/simulation/clock.py
emulo/simulation/fees.py
emulo/simulation/interest.py
emulo/simulation/orderbook.py
emulo/simulation/orders.py
emulo/simulation/portfolio.py
emulo/simulation/runner.py
emulo_backtest-0.1.0.dist-info/licenses/LICENSE
emulo_backtest-0.1.0.dist-info/METADATA
emulo_backtest-0.1.0.dist-info/WHEEL
emulo_backtest-0.1.0.dist-info/top_level.txt
emulo_backtest-0.1.0.dist-info/RECORD
