Metadata-Version: 2.4
Name: emulo-backtest
Version: 0.1.0
Summary: Minimal backtesting for Polymarket/Kalshi prediction markets via Dome API
Home-page: https://github.com/tweidv/emulo-backtest
Author: tweidv
Author-email: tweidevrieze@gmail.com
License: MIT
Project-URL: Bug Tracker, https://github.com/tweidv/emulo-backtest/issues
Project-URL: Documentation, https://github.com/tweidv/emulo-backtest#readme
Project-URL: Source Code, https://github.com/tweidv/emulo-backtest
Keywords: polymarket,kalshi,prediction-markets,backtesting,trading
Classifier: Development Status :: 4 - Beta
Classifier: Intended Audience :: Developers
Classifier: Intended Audience :: Financial and Insurance Industry
Classifier: License :: OSI Approved :: MIT License
Classifier: Programming Language :: Python :: 3
Classifier: Programming Language :: Python :: 3.9
Classifier: Programming Language :: Python :: 3.10
Classifier: Programming Language :: Python :: 3.11
Classifier: Programming Language :: Python :: 3.12
Classifier: Topic :: Office/Business :: Financial :: Investment
Classifier: Operating System :: OS Independent
Requires-Python: >=3.9
License-File: LICENSE
Requires-Dist: dome-api-sdk>=0.1.7
Requires-Dist: python-dotenv>=1.0.0
Dynamic: author
Dynamic: author-email
Dynamic: classifier
Dynamic: description
Dynamic: description-content-type
Dynamic: home-page
Dynamic: keywords
Dynamic: license
Dynamic: license-file
Dynamic: project-url
Dynamic: requires-dist
Dynamic: requires-python
Dynamic: summary
